Metadata-Version: 2.1
Name: tfdec
Version: 2.2
Summary: Сonverting whole natural numbers from and to decimal
Home-page: UNKNOWN
Author-email: igr.tkchv@gmail.com
License: UNKNOWN
Platform: UNKNOWN
